automatminer/__init__.py
automatminer/base.py
automatminer/pipeline.py
automatminer/presets.py
automatminer/automl/__init__.py
automatminer/automl/adaptors.py
automatminer/automl/base.py
automatminer/automl/config/__init__.py
automatminer/automl/config/tpot_configs.py
automatminer/automl/tests/__init__.py
automatminer/automl/tests/mini_automl_df.csv
automatminer/automl/tests/test_adaptors.py
automatminer/automl/tests/test_base.py
automatminer/featurization/__init__.py
automatminer/featurization/base.py
automatminer/featurization/core.py
automatminer/featurization/sets.py
automatminer/featurization/tests/__init__.py
automatminer/featurization/tests/mp_data_with_dos_bandstructure.pickle
automatminer/featurization/tests/test_base.py
automatminer/featurization/tests/test_core.py
automatminer/featurization/tests/test_sets.py
automatminer/preprocessing/__init__.py
automatminer/preprocessing/core.py
automatminer/preprocessing/feature_selection.py
automatminer/preprocessing/tests/__init__.py
automatminer/preprocessing/tests/test_core.py
automatminer/preprocessing/tests/test_featurized_df.csv
automatminer/tests/__init__.py
automatminer/tests/test_base.py
automatminer/tests/test_pipeline.py
automatminer/tests/test_presets.py
automatminer/utils/__init__.py
automatminer/utils/log.py
automatminer/utils/ml.py
automatminer/utils/pkg.py
automatminer/utils/tests/__init__.py
automatminer/utils/tests/test_log.py
automatminer/utils/tests/test_ml.py
automatminer/utils/tests/test_pkg.py
automatminer_dev/__init__.py
automatminer_dev/config.py
automatminer_dev/submit.py
automatminer_dev/graphnet/__init__.py
automatminer_dev/graphnet/cgcnn.py
automatminer_dev/graphnet/megnet.py
automatminer_dev/local/__init__.py
automatminer_dev/local/dummy.py
automatminer_dev/local/nn.py
automatminer_dev/local/rf.py
automatminer_dev/local/diversity/__init__.py
automatminer_dev/local/diversity/diversity.py
automatminer_dev/matbench/__init__.py
automatminer_dev/matbench/castelli.py
automatminer-1.0.3.20200727.dist-info/LICENSE
automatminer-1.0.3.20200727.dist-info/METADATA
automatminer-1.0.3.20200727.dist-info/WHEEL
automatminer-1.0.3.20200727.dist-info/top_level.txt
automatminer-1.0.3.20200727.dist-info/RECORD
