Metadata-Version: 2.1
Name: automatminer
Version: 1.0.3.20200727
Summary: automated machine learning for materials science
Home-page: https://github.com/hackingmaterials/automatminer
Author: ['Alex Dunn', 'Alex Ganose', 'Alireza Faghaninia', 'Qi Wang', 'Anubhav Jain']
Author-email: ardunn@lbl.gov
License: modified BSD
Platform: UNKNOWN
Classifier: Programming Language :: Python :: 3.6
Classifier: Development Status :: 4 - Beta
Classifier: Intended Audience :: Science/Research
Classifier: Intended Audience :: System Administrators
Classifier: Intended Audience :: Information Technology
Classifier: Operating System :: OS Independent
Classifier: Topic :: Other/Nonlisted Topic
Classifier: Topic :: Scientific/Engineering
Requires-Dist: matminer (==0.6.2)
Requires-Dist: pymatgen (==2020.01.28)
Requires-Dist: tpot (==0.11.0)
Requires-Dist: skrebate (==0.6)
Requires-Dist: pyyaml (==5.1.2)
Requires-Dist: scikit-learn (==0.22.2)
